pyrogram_asyncpg_storage/__init__.py
pyrogram_asyncpg_storage-0.1.dist-info/METADATA
pyrogram_asyncpg_storage-0.1.dist-info/WHEEL
pyrogram_asyncpg_storage-0.1.dist-info/top_level.txt
pyrogram_asyncpg_storage-0.1.dist-info/RECORD
