Metadata-Version: 2.1
Name: pyrogram-asyncpg-storage
Version: 0.1
Summary: asyncpg storage for pyrogram
Home-page: https://github.com/drizzt/pyrogram-asyncpg-storage
Author: Timothy Redaelli
Author-email: timothy.redaelli@gmail.com
Classifier: Operating System :: OS Independent
Classifier: Intended Audience :: Developers
Classifier: Programming Language :: Python
Classifier: Programming Language :: Python :: 3.6
Classifier: Programming Language :: Python :: 3.7
Classifier: Programming Language :: Python :: 3.8
Classifier: Programming Language :: Python :: 3.9
Classifier: Programming Language :: Python :: 3.10
Requires-Python: >=3.6.0
Requires-Dist: asyncpg
Requires-Dist: pyrogram
